eandb/__init__.py
eandb/clients/__init__.py
eandb/clients/v2/__init__.py
eandb/models/__init__.py
eandb/models/v2/__init__.py
eandb-0.8.0.dist-info/METADATA
eandb-0.8.0.dist-info/WHEEL
eandb-0.8.0.dist-info/RECORD
