Metadata-Version: 2.3
Name: eandb
Version: 0.8.0
Summary: Python client for EAN-DB API
Home-page: https://github.com/ean-db/python-client
License: MIT
Keywords: barcode,ean,upc,isbn
Author: EAN-DB
Author-email: support@ean-db.com
Requires-Python: >=3.8.1
Classifier: License :: OSI Approved :: MIT License
Classifier: Programming Language :: Python :: 3
Classifier: Programming Language :: Python :: 3.9
Classifier: Programming Language :: Python :: 3.10
Classifier: Programming Language :: Python :: 3.11
Classifier: Programming Language :: Python :: 3.12
Classifier: Programming Language :: Python :: 3.13
Classifier: Topic :: Software Development :: Libraries :: Python Modules
Requires-Dist: httpx (>=0.23.0)
Requires-Dist: pydantic (>=2.0)
Project-URL: Repository, https://github.com/ean-db/python-client
